ballad/__init__.py
ballad/__main__.py
ballad/core.py
ballad/utils.py
ballad-2.0.0.dist-info/LICENSE
ballad-2.0.0.dist-info/METADATA
ballad-2.0.0.dist-info/WHEEL
ballad-2.0.0.dist-info/top_level.txt
ballad-2.0.0.dist-info/RECORD
