Metadata-Version: 2.1
Name: ballad
Version: 2.0.0
Summary: For when Poetry just doesn't work.
Home-page: https://github.com/BD103/Ballad
Author: BD103
Author-email: dont@stalk.me
License: UNKNOWN
Project-URL: Repository, https://github.com/BD103/Ballad
Project-URL: Bug Tracker, https://github.com/BD103/Ballad/issues
Platform: UNKNOWN
Classifier: Programming Language :: Python :: 3
Classifier: Operating System :: OS Independent
Requires-Python: >=3.8
Requires-Dist: tomlkit (<1.0.0,>=0.7.0)
Requires-Dist: click (>=8.0.1)
